{"check_id":"3574eda7-152e-49dd-a393-691c6cc7352e","ingredients":[{"name":"гліцинат магнію","quantity":500,"unit":"мг","type":"active"},{"name":"вітамін В6","quantity":1,"unit":"мг","type":"active"},{"name":"вітамін В12","quantity":1.5,"unit":"мкг","type":"active"},{"name":"МКЦ","quantity":null,"unit":null,"type":"excipient"},{"name":"крохмаль","quantity":null,"unit":null,"type":"excipient"},{"name":"кремнію діоксид","quantity":null,"unit":null,"type":"excipient"},{"name":"стеарат кальцію","quantity":null,"unit":null,"type":"excipient"}],"product_info":{"name":"МАГНІЙ ГЛІЦИНАТ MAGNESIUM GLYCINATE","form":"tablets","quantity":120,"batch_number":"15.09.2025"},"allergens":[],"allergen_statement":null,"mandatory_phrases":{"has_dietary_supplement_label":true,"has_not_medicine":true,"has_not_exceed_dose":true,"has_not_replace_diet":true,"has_keep_away_children":true},"full_text":"# ПОВНИЙ ТЕКСТ З ЕТИКЕТКИ:\n\nABU ukraine\n\nДІЄТИЧНА ДОБАВКА МАГНІЙ ГЛІЦИНАТ MAGNESIUM GLYCINATE\n\nСклад: ГЛІЦИНАТ МАГНІЮ – 500 мг(mg), ВІТАМІН В6 – 1 мг(mg), ВІТАМІН В12 – 1,5 мкг(μg)\n\nДопоміжні речовини: МКЦ, крохмаль, кремнію діоксид, стеарат кальцію.\n\nБез ГМО.\n\nМаса вмісту 1 таблетки: 1200 мг(mg) ±7.5%\n\nДобова доза, рекомендована для щоденного споживання: дорослим по 1-2 таблетки на день під час їжі.\n\nТермін придатності: 2 роки з дати виготовлення.\nНомер партії співпадає з датою виготовлення.\n\nВжити до: 15.09.2027\nПартія NP: 15.09.2025\n\n120 таблеток\n\nISO 22000\nISO 9001\nPET\n\nЗастереження до споживання: ІНДИВІДУАЛЬНА непереносимість компонентів продукту, вагітність, годування груддю. Перед вживанням проконсультуйтесь зі своїм лікарем. Дієтичні добавки не слід використовувати як заміну повноцінного раціону харчування. Не перевищувати зазначену рекомендовану дозу для щоденного споживання. Цей продукт не призначений для діагностики, лікування або запобігання будь-яких захворювань.\nНе є лікарським засобом.\nУмови зберігання: зберігати в сухому, захищеному від світла місці за температури від +5 °C до +25 °C і відносній вологості не більше 75% в недоступному для дітей місці.\nЗамовник (відповідальний за інформацію для споживачів): ТОВ «УКРАЇНСЬКІ ВІТАМІНИ», Україна, Дніпропетровська ОбЛ., М. Дніпро, вул. Сонячна Набережна, буд. 2,\nТел.: +38(097)100-32-75\nABU.COM.UA\nТУ У 10.8-41815746-002:2021\nВиробник: ТОВ «БІО ЛАЙТ»\nУкраїна, Запорізька ОбЛ.,\nм. Запоріжжя,\nвул. Перемоги, буд. 135-А\nТел. +38(096)498-9128","operator":{"name":"ТОВ «УКРАЇНСЬКІ ВІТАМІНИ»","edrpou":"41815746","address":"Україна, Дніпропетровська обл., м. Дніпро, вул. Сонячна Набережна, буд. 2","phone":"+38(097)100-32-75"},"warnings":["індивідуальна непереносимість компонентів продукту","вагітність","годування груддю"],"daily_dose":"дорослим по 1-2 таблетки на день під час їжі","storage":"зберігати в сухому, захищеному від світла місці за температури від +5 °C до +25 °C і відносній вологості не більше 75% в недоступному для дітей місці","manufacturer":{"name":"ТОВ «БІО ЛАЙТ»","address":"Україна, Запорізька обл., м. Запоріжжя, вул. Перемоги, буд. 135-А"},"shelf_life":"2 роки","tech_specs":"ТУ У 10.8-41815746-002:2021","extracted_at":"2025-11-25T19:47:43.726516"}